{
  "endTime" : "2026-02-07T15:29:00Z",
  "aiInterventions" : 0,
  "totalForceApplied" : 3,
  "aiDifficulty" : 0.5,
  "totalDuration" : 1.154829978942871,
  "gameMode" : "Free Play",
  "levelsCompleted" : [

  ],
  "startTime" : "2026-02-07T15:28:59Z",
  "aiMode" : "Off",
  "maxLevel" : 1,
  "sessionId" : "760EC65B-71DD-4033-B251-B6C19A133927",
  "levelConfigs" : [
    {
      "massMultiplier" : 1,
      "lengthMultiplier" : 1,
      "balanceRequiredTime" : 1.5,
      "level" : 1,
      "balanceThreshold" : 0.35,
      "dampingValue" : 0.4,
      "springConstantValue" : 0.2,
      "jiggleIntensity" : 0,
      "initialPerturbation" : 5,
      "gravityMultiplier" : 1
    }
  ],
  "maxScore" : 0,
  "averageBalanceTime" : 0,
  "totalPushes" : 1,
  "aiControlCalls" : 0
}